dynamic_imports/__init__.py
dynamic_imports/importers.py
dynamic_imports/search.py
dynamic_imports-1.1.1.dist-info/METADATA
dynamic_imports-1.1.1.dist-info/WHEEL
dynamic_imports-1.1.1.dist-info/RECORD
